lakeapi2sql-0.9.1.dist-info/METADATA
lakeapi2sql-0.9.1.dist-info/WHEEL
lakeapi2sql-0.9.1.dist-info/license_files/LICENSE
lakeapi2sql/bulk_insert.py
lakeapi2sql/sql_connection.py
lakeapi2sql/utils.py
lakeapi2sql/__init__.py
lakeapi2sql/_lowlevel.pyd
lakeapi2sql-0.9.1.dist-info/RECORD
