Metadata-Version: 2.3
Name: lakeapi2sql
Version: 0.9.1
Classifier: Programming Language :: Rust
Classifier: Programming Language :: Python :: Implementation :: CPython
Classifier: Programming Language :: Python :: Implementation :: PyPy
Requires-Dist: pyarrow >=8.0.0
Requires-Dist: azure-identity >=1.12.0 ; extra == 'azure'
Provides-Extra: azure
License-File: LICENSE
Requires-Python: >=3.10
